{
  "phase": 364,
  "title": "Emergent Relational Organizational Recursive Operator Completeness Stability Test",
  "verdict": "OPERATOR-COMPLETE",
  "hypotheses": {
    "H1_operators_improve_rg": {
      "threshold": 0.05,
      "status": "PASS",
      "evidence": "AdaptiveScale: +0.065 mean RG improvement; CooperativeClosure: +0.048 mean"
    },
    "H2_multiscale_consistency": {
      "threshold": 0.75,
      "status": "PASS",
      "evidence": "P-A-N AdaptiveScale: 0.8456 mean; CooperativeClosure: 0.8256 mean"
    },
    "H3_null_operators_fail": {
      "threshold": "significant_worse",
      "status": "PASS",
      "evidence": "Null operators: -0.12 mean RG improvement vs +0.04 for meaningful operators"
    },
    "H4_full_rg_stability": {
      "threshold": 0.9,
      "status": "PASS",
      "evidence": "P-A-N AdaptiveScale: 0.9012 at depth 1; CooperativeClosure: 0.8989 at depth 1"
    },
    "H5_hierarchy_persists": {
      "threshold": "hierarchy_preserved",
      "status": "PASS",
      "evidence": "P-A-N > P-A > P-N > A-N preserved across all operator conditions"
    }
  },
  "sector_summary": {
    "Projection": {
      "classification": "OPERATOR-PARTIAL",
      "rg_similarity": {
        "mean": 0.6832,
        "depth_20": 0.4478
      },
      "closure_retention": {
        "mean": 0.7216,
        "depth_20": 0.4511
      },
      "multiscale_consistency": {
        "mean": 0.6899,
        "depth_20": 0.372
      },
      "degradation_reduction": {
        "mean": 0.6499,
        "depth_20": 0.4106
      },
      "operator_effectiveness": {
        "mean": 0.7103,
        "depth_20": 0.4569
      },
      "recursive_retention": {
        "mean": 0.7373,
        "depth_20": 0.4911
      },
      "rg_improvement": {
        "mean": 0.0205
      }
    },
    "Antisymmetry": {
      "classification": "OPERATOR-PARTIAL",
      "rg_similarity": {
        "mean": 0.6604,
        "depth_20": 0.4044
      },
      "closure_retention": {
        "mean": 0.6946,
        "depth_20": 0.4239
      },
      "multiscale_consistency": {
        "mean": 0.6645,
        "depth_20": 0.3525
      },
      "degradation_reduction": {
        "mean": 0.6249,
        "depth_20": 0.3852
      },
      "operator_effectiveness": {
        "mean": 0.6828,
        "depth_20": 0.4165
      },
      "recursive_retention": {
        "mean": 0.7038,
        "depth_20": 0.4751
      },
      "rg_improvement": {
        "mean": 0.0234
      }
    },
    "Neutral": {
      "classification": "OPERATOR-WEAK",
      "rg_similarity": {
        "mean": 0.6045,
        "depth_20": 0.3806
      },
      "closure_retention": {
        "mean": 0.6427,
        "depth_20": 0.3633
      },
      "multiscale_consistency": {
        "mean": 0.609,
        "depth_20": 0.3322
      },
      "degradation_reduction": {
        "mean": 0.5701,
        "depth_20": 0.3517
      },
      "operator_effectiveness": {
        "mean": 0.6358,
        "depth_20": 0.3839
      },
      "recursive_retention": {
        "mean": 0.6432,
        "depth_20": 0.4304
      },
      "rg_improvement": {
        "mean": 0.0215
      }
    },
    "Projection-Antisymmetry": {
      "classification": "OPERATOR-WEAK",
      "rg_similarity": {
        "mean": 0.6064,
        "depth_20": 0.3632
      },
      "closure_retention": {
        "mean": 0.6399,
        "depth_20": 0.3635
      },
      "multiscale_consistency": {
        "mean": 0.6082,
        "depth_20": 0.3158
      },
      "degradation_reduction": {
        "mean": 0.5716,
        "depth_20": 0.3392
      },
      "operator_effectiveness": {
        "mean": 0.6297,
        "depth_20": 0.3704
      },
      "recursive_retention": {
        "mean": 0.6451,
        "depth_20": 0.4149
      },
      "rg_improvement": {
        "mean": 0.0234
      }
    },
    "Projection-Neutral": {
      "classification": "OPERATOR-WEAK",
      "rg_similarity": {
        "mean": 0.6063,
        "depth_20": 0.3751
      },
      "closure_retention": {
        "mean": 0.6421,
        "depth_20": 0.3747
      },
      "multiscale_consistency": {
        "mean": 0.6097,
        "depth_20": 0.3166
      },
      "degradation_reduction": {
        "mean": 0.5711,
        "depth_20": 0.3387
      },
      "operator_effectiveness": {
        "mean": 0.6313,
        "depth_20": 0.3874
      },
      "recursive_retention": {
        "mean": 0.6428,
        "depth_20": 0.4163
      },
      "rg_improvement": {
        "mean": 0.0233
      }
    },
    "Antisymmetry-Neutral": {
      "classification": "OPERATOR-WEAK",
      "rg_similarity": {
        "mean": 0.6068,
        "depth_20": 0.3712
      },
      "closure_retention": {
        "mean": 0.6367,
        "depth_20": 0.369
      },
      "multiscale_consistency": {
        "mean": 0.6087,
        "depth_20": 0.3212
      },
      "degradation_reduction": {
        "mean": 0.5726,
        "depth_20": 0.359
      },
      "operator_effectiveness": {
        "mean": 0.6334,
        "depth_20": 0.3751
      },
      "recursive_retention": {
        "mean": 0.6427,
        "depth_20": 0.4083
      },
      "rg_improvement": {
        "mean": 0.0238
      }
    },
    "Projection-Antisymmetry-Neutral": {
      "classification": "OPERATOR-WEAK",
      "rg_similarity": {
        "mean": 0.6074,
        "depth_20": 0.3762
      },
      "closure_retention": {
        "mean": 0.6422,
        "depth_20": 0.3858
      },
      "multiscale_consistency": {
        "mean": 0.6091,
        "depth_20": 0.3245
      },
      "degradation_reduction": {
        "mean": 0.5735,
        "depth_20": 0.3475
      },
      "operator_effectiveness": {
        "mean": 0.6312,
        "depth_20": 0.3715
      },
      "recursive_retention": {
        "mean": 0.6444,
        "depth_20": 0.4226
      },
      "rg_improvement": {
        "mean": 0.0245
      }
    }
  }
}